.travis.yml
LICENSE
MANIFEST.in
README.rst
setup.cfg
setup.py
libextract/__init__.py
libextract/_compat.py
libextract/api.py
libextract/core.py
libextract/xpaths.py
libextract.egg-info/PKG-INFO
libextract.egg-info/SOURCES.txt
libextract.egg-info/dependency_links.txt
libextract.egg-info/not-zip-safe
libextract.egg-info/requires.txt
libextract.egg-info/top_level.txt
tests/__init__.py
tests/__init__.pyc
tests/conftest.pyc
tests/fixtures.py
tests/fixtures.pyc
tests/test_api.py
tests/test_core.py
tests/test_coretools.pyc
tests/test_formatters.pyc
tests/test_html.pyc
tests/test_libextract.pyc
tests/__pycache__/__init__.cpython-34.pyc
tests/__pycache__/conftest.cpython-34.pyc
tests/__pycache__/test_api.cpython-27-PYTEST.pyc
tests/__pycache__/test_article.cpython-27-PYTEST.pyc
tests/__pycache__/test_baskets.cpython-27-PYTEST.pyc
tests/__pycache__/test_clean.cpython-27-PYTEST.pyc
tests/__pycache__/test_core.cpython-27-PYTEST.pyc
tests/__pycache__/test_coretools.cpython-27-PYTEST.pyc
tests/__pycache__/test_extractor.cpython-27-PYTEST.pyc
tests/__pycache__/test_format.cpython-27-PYTEST.pyc
tests/__pycache__/test_formatters.cpython-27-PYTEST.pyc
tests/__pycache__/test_libextract.cpython-27-PYTEST.pyc
tests/__pycache__/test_maximizers.cpython-27-PYTEST.pyc
tests/__pycache__/test_metrics.cpython-27-PYTEST.pyc
tests/__pycache__/test_ors.cpython-27-PYTEST.pyc
tests/__pycache__/test_pruners.cpython-27-PYTEST.pyc
tests/__pycache__/test_quantifiers.cpython-27-PYTEST.pyc
tests/__pycache__/test_selectors.cpython-27-PYTEST.pyc
tests/__pycache__/test_tabular.cpython-27-PYTEST.pyc
tests/assets/__init__.pyc
tests/assets/full_of_foos.html
tests/html/__init__.pyc
tests/html/test_article.pyc
tests/html/test_commons.pyc
tests/html/test_tabular.pyc
tests/html/test_text.pyc
tests/html/__pycache__/test_article.cpython-27-PYTEST.pyc
tests/html/__pycache__/test_tabular.cpython-27-PYTEST.pyc