Metadata-Version: 1.0
Name: libextract
Version: 0.0.12
Summary: A HT/XML web scraping tool
Home-page: https://github.com/datalib/libextract
Author: Rodrigo Palacios, Eeo Jun
Author-email: rodrigopala91@gmail.com, packwolf58@gmail.com
License: MIT
Keywords: extract extraction main article text html data-extraction data              content-extraction content unsupervised classification machine              learning AI artificial intelligence ML
Platform: any
